jupyhai/__init__.py
jupyhai/_version.py
jupyhai/api_urls.py
jupyhai/consts.py
jupyhai/excs.py
jupyhai/preparer.py
jupyhai/yaml_generator.py
jupyhai/cli/__init__.py
jupyhai/cli/__main__.py
jupyhai/handlers/__init__.py
jupyhai/handlers/base.py
jupyhai/handlers/environments.py
jupyhai/handlers/events.py
jupyhai/handlers/execute.py
jupyhai/handlers/execution_url.py
jupyhai/handlers/executions.py
jupyhai/handlers/hello.py
jupyhai/handlers/images.py
jupyhai/handlers/init.py
jupyhai/handlers/login.py
jupyhai/handlers/logout.py
jupyhai/handlers/notebook_download.py
jupyhai/handlers/output_download.py
jupyhai/handlers/outputs.py
jupyhai/handlers/prepare.py
jupyhai/handlers/projects.py
jupyhai/handlers/settings.py
jupyhai/handlers/stop.py
jupyhai/labextension/package.json
jupyhai/labextension/static/106.ea885be6902e009f8a52.js
jupyhai/labextension/static/177.a0ae7ab49292d53d0347.js
jupyhai/labextension/static/184.f1afd45e36f3c55a7553.js
jupyhai/labextension/static/184.f1afd45e36f3c55a7553.js.LICENSE.txt
jupyhai/labextension/static/1c7513c537e6e8c4be19.svg
jupyhai/labextension/static/267.1c62a9924b6fd41c8d01.js
jupyhai/labextension/static/31f6a7e66f235722c5b07783cb115dfd7bedbb981b9bbaf42989bdbe187d7107.gif
jupyhai/labextension/static/324.cd4393b8b8f1a0f13b28.js
jupyhai/labextension/static/32a8bb6653788d29b0070efb65eb376410c7b234f1d5e08db997eef203da854c.png
jupyhai/labextension/static/48.9e93b916a738a16f2641.js
jupyhai/labextension/static/486.438e84ac132d64a46c37.js
jupyhai/labextension/static/486.438e84ac132d64a46c37.js.LICENSE.txt
jupyhai/labextension/static/669.551cf9f801b57512f005.js
jupyhai/labextension/static/6f55a4d7981843697a3c.png
jupyhai/labextension/static/70.7e3fe199c9e4bcc47464.js
jupyhai/labextension/static/703.9aa32ddf865824390dfc.js
jupyhai/labextension/static/703.9aa32ddf865824390dfc.js.LICENSE.txt
jupyhai/labextension/static/755.accb12cbfc09123e1402.js
jupyhai/labextension/static/755.accb12cbfc09123e1402.js.LICENSE.txt
jupyhai-1.7.0.dist-info/METADATA
jupyhai-1.7.0.dist-info/WHEEL
jupyhai-1.7.0.dist-info/entry_points.txt
jupyhai-1.7.0.dist-info/top_level.txt
jupyhai-1.7.0.dist-info/RECORD
