Metadata-Version: 2.1
Name: jupyhai
Version: 1.7.0
Summary: Jupyter notebook / JupyterLab extension to execute notebooks remotely on Minihai or Valohai host.
Home-page: https://github.com/valohai/jupyhai
Author: valohai
Author-email: info@valohai.com
License: MIT
Keywords: Jupyter,JupyterLab,JupyterLab3
Platform: Linux
Platform: Mac OS X
Platform: Windows
Classifier: License :: OSI Approved :: BSD License
Classifier: Programming Language :: Python
Classifier: Programming Language :: Python :: 3
Classifier: Programming Language :: Python :: 3.6
Classifier: Programming Language :: Python :: 3.7
Classifier: Programming Language :: Python :: 3.8
Classifier: Programming Language :: Python :: 3.9
Classifier: Framework :: Jupyter
Classifier: Framework :: Jupyter :: JupyterLab
Classifier: Framework :: Jupyter :: JupyterLab :: 3
Classifier: Framework :: Jupyter :: JupyterLab :: Extensions
Classifier: Framework :: Jupyter :: JupyterLab :: Extensions :: Prebuilt
Requires-Python: >=3.6
Requires-Dist: valohai-cli (>=0.21.0)
Requires-Dist: valohai-yaml (>=0.23.0)
Requires-Dist: valohai-utils (>=0.3.0)
Requires-Dist: aiohttp (~=3.7)
